Compiled from "Test3.java"
public class cn.howardliu.tutorials.core.stringfor.Test3 {
  public cn.howardliu.tutorials.core.stringfor.Test3();
    Code:
       0: aload_0
       1: invokespecial #1                  // Method java/lang/Object."<init>":()V
       4: return

  public java.lang.String toString();
    Code:
       0: new           #2                  // class java/lang/StringBuilder
       3: dup
       4: invokespecial #3                  // Method java/lang/StringBuilder."<init>":()V
       7: astore_1
       8: iconst_0
       9: istore_2
      10: iload_2
      11: bipush        10
      13: if_icmpge     30
      16: aload_1
      17: invokestatic  #4                  // Method java/lang/System.currentTimeMillis:()J
      20: invokevirtual #5                  // Method java/lang/StringBuilder.append:(J)Ljava/lang/StringBuilder;
      23: pop
      24: iinc          2, 1
      27: goto          10
      30: aload_1
      31: invokevirtual #6                  // Method java/lang/StringBuilder.toString:()Ljava/lang/String;
      34: areturn
}
